azure/mgmt/healthbot/__init__.py
azure/mgmt/healthbot/_configuration.py
azure/mgmt/healthbot/_health_bot_mgmt_client.py
azure/mgmt/healthbot/_patch.py
azure/mgmt/healthbot/_serialization.py
azure/mgmt/healthbot/_vendor.py
azure/mgmt/healthbot/_version.py
azure/mgmt/healthbot/py.typed
azure/mgmt/healthbot/aio/__init__.py
azure/mgmt/healthbot/aio/_configuration.py
azure/mgmt/healthbot/aio/_health_bot_mgmt_client.py
azure/mgmt/healthbot/aio/_patch.py
azure/mgmt/healthbot/aio/operations/__init__.py
azure/mgmt/healthbot/aio/operations/_bots_operations.py
azure/mgmt/healthbot/aio/operations/_operations.py
azure/mgmt/healthbot/aio/operations/_patch.py
azure/mgmt/healthbot/models/__init__.py
azure/mgmt/healthbot/models/_health_bot_mgmt_client_enums.py
azure/mgmt/healthbot/models/_models_py3.py
azure/mgmt/healthbot/models/_patch.py
azure/mgmt/healthbot/operations/__init__.py
azure/mgmt/healthbot/operations/_bots_operations.py
azure/mgmt/healthbot/operations/_operations.py
azure/mgmt/healthbot/operations/_patch.py
azure_mgmt_healthbot-1.0.0b2.dist-info/LICENSE
azure_mgmt_healthbot-1.0.0b2.dist-info/METADATA
azure_mgmt_healthbot-1.0.0b2.dist-info/WHEEL
azure_mgmt_healthbot-1.0.0b2.dist-info/top_level.txt
azure_mgmt_healthbot-1.0.0b2.dist-info/RECORD
